{
 "custom_fields": [
  {
   "_assign": null, 
   "_comments": null, 
   "_liked_by": null, 
   "_user_tags": null, 
   "allow_on_submit": 0, 
   "bold": 0, 
   "collapsible": 0, 
   "collapsible_depends_on": null, 
   "columns": 0, 
   "creation": "2019-10-18 15:56:27.348721", 
   "default": null, 
   "depends_on": null, 
   "description": null, 
   "docstatus": 0, 
   "dt": "Purchase Order Item", 
   "fetch_from": null, 
   "fetch_if_empty": 0, 
   "fieldname": "selling_price", 
   "fieldtype": "Currency", 
   "hidden": 0, 
   "idx": 18, 
   "ignore_user_permissions": 0, 
   "ignore_xss_filter": 0, 
   "in_global_search": 0, 
   "in_list_view": 0, 
   "in_standard_filter": 0, 
   "insert_after": "sec_break1", 
   "label": "Selling Price", 
   "modified": "2019-10-18 15:56:27.348721", 
   "modified_by": "Administrator", 
   "name": "Purchase Order Item-selling_price", 
   "no_copy": 0, 
   "options": null, 
   "owner": "Administrator", 
   "parent": null, 
   "parentfield": null, 
   "parenttype": null, 
   "permlevel": 0, 
   "precision": "", 
   "print_hide": 0, 
   "print_hide_if_no_value": 0, 
   "print_width": null, 
   "read_only": 1, 
   "report_hide": 0, 
   "reqd": 0, 
   "search_index": 0, 
   "translatable": 0, 
   "unique": 0, 
   "width": null
  }
 ], 
 "custom_perms": [], 
 "doctype": "Purchase Order Item", 
 "property_setters": [
  {
   "_assign": null, 
   "_comments": null, 
   "_liked_by": null, 
   "_user_tags": null, 
   "creation": "2019-10-18 15:56:27.279778", 
   "default_value": null, 
   "doc_type": "Purchase Order Item", 
   "docstatus": 0, 
   "doctype_or_field": "DocType", 
   "field_name": null, 
   "idx": 0, 
   "modified": "2019-10-18 15:56:27.279778", 
   "modified_by": "Administrator", 
   "name": "Purchase Order Item-read_only_onload", 
   "owner": "Administrator", 
   "parent": null, 
   "parentfield": null, 
   "parenttype": null, 
   "property": "read_only_onload", 
   "property_type": "Check", 
   "value": null
  }, 
  {
   "_assign": null, 
   "_comments": null, 
   "_liked_by": null, 
   "_user_tags": null, 
   "creation": "2019-10-01 22:32:15.383011", 
   "default_value": null, 
   "doc_type": "Purchase Order Item", 
   "docstatus": 0, 
   "doctype_or_field": "DocField", 
   "field_name": "schedule_date", 
   "idx": 0, 
   "modified": "2019-10-01 22:32:15.383011", 
   "modified_by": "accounts@sbkwt.com", 
   "name": "Purchase Order Item-schedule_date-columns", 
   "owner": "accounts@sbkwt.com", 
   "parent": null, 
   "parentfield": null, 
   "parenttype": null, 
   "property": "columns", 
   "property_type": "Int", 
   "value": "1"
  }, 
  {
   "_assign": null, 
   "_comments": null, 
   "_liked_by": null, 
   "_user_tags": null, 
   "creation": "2019-10-01 22:22:29.240508", 
   "default_value": null, 
   "doc_type": "Purchase Order Item", 
   "docstatus": 0, 
   "doctype_or_field": "DocField", 
   "field_name": "uom", 
   "idx": 0, 
   "modified": "2019-10-01 22:22:29.240508", 
   "modified_by": "accounts@sbkwt.com", 
   "name": "Purchase Order Item-uom-columns", 
   "owner": "accounts@sbkwt.com", 
   "parent": null, 
   "parentfield": null, 
   "parenttype": null, 
   "property": "columns", 
   "property_type": "Int", 
   "value": "1"
  }, 
  {
   "_assign": null, 
   "_comments": null, 
   "_liked_by": null, 
   "_user_tags": null, 
   "creation": "2019-10-01 22:21:44.243868", 
   "default_value": null, 
   "doc_type": "Purchase Order Item", 
   "docstatus": 0, 
   "doctype_or_field": "DocField", 
   "field_name": "uom", 
   "idx": 0, 
   "modified": "2019-10-01 22:21:44.243868", 
   "modified_by": "accounts@sbkwt.com", 
   "name": "Purchase Order Item-uom-in_list_view", 
   "owner": "accounts@sbkwt.com", 
   "parent": null, 
   "parentfield": null, 
   "parenttype": null, 
   "property": "in_list_view", 
   "property_type": "Check", 
   "value": "1"
  }, 
  {
   "_assign": null, 
   "_comments": null, 
   "_liked_by": null, 
   "_user_tags": null, 
   "creation": "2019-07-28 19:39:03.068492", 
   "default_value": null, 
   "doc_type": "Purchase Order Item", 
   "docstatus": 0, 
   "doctype_or_field": "DocField", 
   "field_name": "item_weight_details", 
   "idx": 0, 
   "modified": "2019-07-28 19:39:03.068492", 
   "modified_by": "accounts@sbkwt.com", 
   "name": "Purchase Order Item-item_weight_details-hidden", 
   "owner": "accounts@sbkwt.com", 
   "parent": null, 
   "parentfield": null, 
   "parenttype": null, 
   "property": "hidden", 
   "property_type": "Check", 
   "value": "1"
  }, 
  {
   "_assign": null, 
   "_comments": null, 
   "_liked_by": null, 
   "_user_tags": null, 
   "creation": "2019-07-20 13:43:18.418285", 
   "default_value": null, 
   "doc_type": "Purchase Order Item", 
   "docstatus": 0, 
   "doctype_or_field": "DocField", 
   "field_name": "item_code", 
   "idx": 0, 
   "modified": "2019-07-20 13:43:18.418285", 
   "modified_by": "accounts@sbkwt.com", 
   "name": "Purchase Order Item-item_code-columns", 
   "owner": "accounts@sbkwt.com", 
   "parent": null, 
   "parentfield": null, 
   "parenttype": null, 
   "property": "columns", 
   "property_type": "Int", 
   "value": "5"
  }, 
  {
   "_assign": null, 
   "_comments": null, 
   "_liked_by": null, 
   "_user_tags": null, 
   "creation": "2019-07-20 13:39:39.093037", 
   "default_value": null, 
   "doc_type": "Purchase Order Item", 
   "docstatus": 0, 
   "doctype_or_field": "DocField", 
   "field_name": "rate", 
   "idx": 0, 
   "modified": "2019-07-20 13:39:39.093037", 
   "modified_by": "accounts@sbkwt.com", 
   "name": "Purchase Order Item-rate-columns", 
   "owner": "accounts@sbkwt.com", 
   "parent": null, 
   "parentfield": null, 
   "parenttype": null, 
   "property": "columns", 
   "property_type": "Int", 
   "value": "1"
  }, 
  {
   "_assign": null, 
   "_comments": null, 
   "_liked_by": null, 
   "_user_tags": null, 
   "creation": "2019-07-20 13:39:39.076981", 
   "default_value": null, 
   "doc_type": "Purchase Order Item", 
   "docstatus": 0, 
   "doctype_or_field": "DocField", 
   "field_name": "stock_uom", 
   "idx": 0, 
   "modified": "2019-07-20 13:39:39.076981", 
   "modified_by": "accounts@sbkwt.com", 
   "name": "Purchase Order Item-stock_uom-label", 
   "owner": "accounts@sbkwt.com", 
   "parent": null, 
   "parentfield": null, 
   "parenttype": null, 
   "property": "label", 
   "property_type": "Data", 
   "value": "Unit"
  }, 
  {
   "_assign": null, 
   "_comments": null, 
   "_liked_by": null, 
   "_user_tags": null, 
   "creation": "2019-04-16 15:19:51.841738", 
   "default_value": null, 
   "doc_type": "Purchase Order Item", 
   "docstatus": 0, 
   "doctype_or_field": "DocField", 
   "field_name": "stock_uom", 
   "idx": 0, 
   "modified": "2019-04-16 15:19:51.841738", 
   "modified_by": "Administrator", 
   "name": "Purchase Order Item-stock_uom-columns", 
   "owner": "Administrator", 
   "parent": null, 
   "parentfield": null, 
   "parenttype": null, 
   "property": "columns", 
   "property_type": "Int", 
   "value": "1"
  }
 ], 
 "sync_on_migrate": 1
}